kneebow/__init__.py
kneebow/rotor.py
kneebow-1.0.1.dist-info/LICENSE.md
kneebow-1.0.1.dist-info/METADATA
kneebow-1.0.1.dist-info/WHEEL
kneebow-1.0.1.dist-info/top_level.txt
kneebow-1.0.1.dist-info/RECORD
