Metadata-Version: 2.1
Name: kneebow
Version: 1.0.1
Summary: Knee or elbow detection for curves
Home-page: https://github.com/georg-un/kneebow
Download-URL: https://github.com/georg-un/kneebow/archive/v1.0.1.tar.gz
Author: Georg Unterholzner
Author-email: georg.unterholzner.coding@gmail.com
License: MIT
Classifier: Development Status :: 5 - Production/Stable
Classifier: Intended Audience :: Science/Research
Classifier: Topic :: Scientific/Engineering :: Information Analysis
Classifier: License :: OSI Approved :: MIT License
Classifier: Programming Language :: Python :: 3
Classifier: Programming Language :: Python :: 3.4
Classifier: Programming Language :: Python :: 3.5
Classifier: Programming Language :: Python :: 3.6
Classifier: Programming Language :: Python :: 3.7
Classifier: Programming Language :: Python :: 3.8
Classifier: Programming Language :: Python :: 3.9
Requires-Python: >=3.4
License-File: LICENSE.md
